{
  "rows": 2,
  "columns": 19,
  "missing_values": {
    "url": 2,
    "title": 2,
    "paragraph": 2,
    "heading_count": 0,
    "link_count": 0,
    "table_count": 0,
    "html_source": 2,
    "url_day": 2,
    "url_month": 2,
    "url_year": 2,
    "title_day": 2,
    "title_month": 2,
    "title_year": 2,
    "paragraph_day": 2,
    "paragraph_month": 2,
    "paragraph_year": 2,
    "html_source_day": 2,
    "html_source_month": 2,
    "html_source_year": 2
  },
  "missing_pct": {
    "url": 100.0,
    "title": 100.0,
    "paragraph": 100.0,
    "heading_count": 0.0,
    "link_count": 0.0,
    "table_count": 0.0,
    "html_source": 100.0,
    "url_day": 100.0,
    "url_month": 100.0,
    "url_year": 100.0,
    "title_day": 100.0,
    "title_month": 100.0,
    "title_year": 100.0,
    "paragraph_day": 100.0,
    "paragraph_month": 100.0,
    "paragraph_year": 100.0,
    "html_source_day": 100.0,
    "html_source_month": 100.0,
    "html_source_year": 100.0
  },
  "duplicates": 1,
  "dtypes": {
    "url": "float64",
    "title": "float64",
    "paragraph": "float64",
    "heading_count": "int64",
    "link_count": "int64",
    "table_count": "int64",
    "html_source": "float64",
    "url_day": "float64",
    "url_month": "float64",
    "url_year": "float64",
    "title_day": "float64",
    "title_month": "float64",
    "title_year": "float64",
    "paragraph_day": "float64",
    "paragraph_month": "float64",
    "paragraph_year": "float64",
    "html_source_day": "float64",
    "html_source_month": "float64",
    "html_source_year": "float64"
  },
  "numeric_summary": {
    "url": {
      "count": 0.0,
      "mean": null,
      "std": null,
      "min": null,
      "25%": null,
      "50%": null,
      "75%": null,
      "max": null
    },
    "title": {
      "count": 0.0,
      "mean": null,
      "std": null,
      "min": null,
      "25%": null,
      "50%": null,
      "75%": null,
      "max": null
    },
    "paragraph": {
      "count": 0.0,
      "mean": null,
      "std": null,
      "min": null,
      "25%": null,
      "50%": null,
      "75%": null,
      "max": null
    },
    "heading_count": {
      "count": 2.0,
      "mean": 1.0,
      "std": 0.0,
      "min": 1.0,
      "25%": 1.0,
      "50%": 1.0,
      "75%": 1.0,
      "max": 1.0
    },
    "link_count": {
      "count": 2.0,
      "mean": 1.0,
      "std": 0.0,
      "min": 1.0,
      "25%": 1.0,
      "50%": 1.0,
      "75%": 1.0,
      "max": 1.0
    },
    "table_count": {
      "count": 2.0,
      "mean": 0.0,
      "std": 0.0,
      "min": 0.0,
      "25%": 0.0,
      "50%": 0.0,
      "75%": 0.0,
      "max": 0.0
    },
    "html_source": {
      "count": 0.0,
      "mean": null,
      "std": null,
      "min": null,
      "25%": null,
      "50%": null,
      "75%": null,
      "max": null
    },
    "url_day": {
      "count": 0.0,
      "mean": null,
      "std": null,
      "min": null,
      "25%": null,
      "50%": null,
      "75%": null,
      "max": null
    },
    "url_month": {
      "count": 0.0,
      "mean": null,
      "std": null,
      "min": null,
      "25%": null,
      "50%": null,
      "75%": null,
      "max": null
    },
    "url_year": {
      "count": 0.0,
      "mean": null,
      "std": null,
      "min": null,
      "25%": null,
      "50%": null,
      "75%": null,
      "max": null
    },
    "title_day": {
      "count": 0.0,
      "mean": null,
      "std": null,
      "min": null,
      "25%": null,
      "50%": null,
      "75%": null,
      "max": null
    },
    "title_month": {
      "count": 0.0,
      "mean": null,
      "std": null,
      "min": null,
      "25%": null,
      "50%": null,
      "75%": null,
      "max": null
    },
    "title_year": {
      "count": 0.0,
      "mean": null,
      "std": null,
      "min": null,
      "25%": null,
      "50%": null,
      "75%": null,
      "max": null
    },
    "paragraph_day": {
      "count": 0.0,
      "mean": null,
      "std": null,
      "min": null,
      "25%": null,
      "50%": null,
      "75%": null,
      "max": null
    },
    "paragraph_month": {
      "count": 0.0,
      "mean": null,
      "std": null,
      "min": null,
      "25%": null,
      "50%": null,
      "75%": null,
      "max": null
    },
    "paragraph_year": {
      "count": 0.0,
      "mean": null,
      "std": null,
      "min": null,
      "25%": null,
      "50%": null,
      "75%": null,
      "max": null
    },
    "html_source_day": {
      "count": 0.0,
      "mean": null,
      "std": null,
      "min": null,
      "25%": null,
      "50%": null,
      "75%": null,
      "max": null
    },
    "html_source_month": {
      "count": 0.0,
      "mean": null,
      "std": null,
      "min": null,
      "25%": null,
      "50%": null,
      "75%": null,
      "max": null
    },
    "html_source_year": {
      "count": 0.0,
      "mean": null,
      "std": null,
      "min": null,
      "25%": null,
      "50%": null,
      "75%": null,
      "max": null
    }
  },
  "skewness": {}
}