{
    "input_dataframe_path": "storage\\dataframes\\extracted_31af8085-a023-4354-bb2d-58f464febf55.csv",
    "cleaned_dataframe_path": "storage\\cleaned_data\\cleaned_5c0079e9-8def-48cd-855a-40f61dc61d95.csv",
    "profile_path": "storage\\profiles\\profile_5ecae5d3-2df4-46fd-a419-ccbc0bf9a95a.json",
    "metadata_path": null,
    "logs": [
        "Loading dataframe",
        "Loaded dataframe with shape (109, 7)",
        "Data profiling completed",
        "Missing values handled",
        "Duplicates removed",
        "Text standardized",
        "Numeric validation completed",
        "Cleaned dataframe saved at storage\\cleaned_data\\cleaned_5c0079e9-8def-48cd-855a-40f61dc61d95.csv"
    ],
    "quality_report": {
        "final_rows": 109,
        "final_columns": 7,
        "missing_after_cleaning": {
            "url": 0,
            "title": 0,
            "paragraph": 0,
            "heading_count": 0,
            "link_count": 0,
            "table_count": 0,
            "html_source": 0
        },
        "duplicates_after_cleaning": 0
    }
}